compileall2.py
compileall2-0.8.0.dist-info/LICENSE
compileall2-0.8.0.dist-info/METADATA
compileall2-0.8.0.dist-info/WHEEL
compileall2-0.8.0.dist-info/entry_points.txt
compileall2-0.8.0.dist-info/top_level.txt
compileall2-0.8.0.dist-info/RECORD
