Metadata-Version: 2.1
Name: compileall2
Version: 0.8.0
Summary: Enhanced Python `compileall` module
Home-page: https://github.com/fedora-python/compileall2
Author: Lumír Balhar
Author-email: frenzy.madness@gmail.com
License: PSFv2
Classifier: Development Status :: 4 - Beta
Classifier: Intended Audience :: Developers
Classifier: Programming Language :: Python :: 3
Classifier: Programming Language :: Python :: 3.6
Classifier: Programming Language :: Python :: 3.7
Classifier: Programming Language :: Python :: 3.8
Classifier: Programming Language :: Python :: 3.9
Classifier: Programming Language :: Python :: 3.10
Classifier: Programming Language :: Python :: 3.11
Classifier: Programming Language :: Python :: 3.12
Classifier: Programming Language :: Python :: 3.13
Classifier: Programming Language :: Python :: Implementation :: CPython
Classifier: Programming Language :: Python :: Implementation :: PyPy
Classifier: License :: OSI Approved :: Python Software Foundation License
Classifier: Operating System :: POSIX :: Linux
Classifier: Topic :: Software Development :: Compilers
License-File: LICENSE
